{
  "tags": [
    {
      "name": "release",
      "version": "1.0.0",
      "commit": "51c38e9",
      "upstream": "Releases",
      "lastUpdated": "2021-11-01T15:56:35.668Z"
    },
    {
      "name": "testing",
      "version": "",
      "commit": "",
      "upstream": "",
      "lastUpdated": ""
    },
    {
      "name": "nightly",
      "version": "215b4cf5b29244bc23ed3f65ab627da7b5e21666",
      "commit": "7bac17e",
      "upstream": "Every commit to master",
      "lastUpdated": "2021-11-01T16:04:38.783Z"
    }
  ],
  "pulls": 6069,
  "stars": 1
}
